ymvas/__init__.py
ymvas/__main__.py
ymvas/client.py
ymvas/operator.py
ymvas/settings.py
ymvas/config/__init__.py
ymvas/config/ycommands.py
ymvas/config/yendpoints.py
ymvas/config/yevents.py
ymvas/config/ysettings.py
ymvas/config/ytasks.py
ymvas/config/components/__init__.py
ymvas/config/components/contact.py
ymvas/config/components/endpoint.py
ymvas/config/components/event.py
ymvas/config/components/ref.py
ymvas/config/components/task.py
ymvas/services/__init__.py
ymvas/services/api.py
ymvas/services/compiler.py
ymvas/services/env.py
ymvas/services/gits.py
ymvas/services/referer.py
ymvas/services/templates/__init__.py
ymvas/services/templates/creator.py
ymvas/services/templates/account/.gitignore
ymvas/services/templates/account/.ymvas/commands/test.py
ymvas/services/templates/account/.ymvas/settings/settings.yaml
ymvas/services/templates/account/.ymvas/tasks/setup
ymvas/services/templates/account/contacts/example.yaml
ymvas/services/templates/account/documents/info.txt
ymvas/services/templates/account/spaces/.gitignore
ymvas/services/templates/default/.gitignore
ymvas/services/templates/default/.ymvas/commands/test.py
ymvas/services/templates/default/.ymvas/settings/settings.yaml
ymvas/services/templates/default/.ymvas/tasks/setup
ymvas/services/templates/local/.ymvas/commands/test.py
ymvas/services/templates/local/.ymvas/settings/settings.yaml
ymvas/services/templates/local/.ymvas/tasks/setup
ymvas/utils/__init__.py
ymvas/utils/errors.py
ymvas/utils/files.py
ymvas/utils/gits.py
ymvas/utils/logger.py
ymvas/utils/messages.py
ymvas/utils/system.py
ymvas-1.3.6.dist-info/METADATA
ymvas-1.3.6.dist-info/WHEEL
ymvas-1.3.6.dist-info/entry_points.txt
ymvas-1.3.6.dist-info/top_level.txt
ymvas-1.3.6.dist-info/RECORD
