Metadata-Version: 2.4
Name: ymvas
Version: 1.3.6
Summary: Ymvas - handle your life like a developer!
Author-email: Vasyl Yovdiy <vas@ymvas.com>
License: MIT
Requires-Python: >=3.12
Requires-Dist: requests
Requires-Dist: PyYAML
Requires-Dist: python-dotenv
Requires-Dist: croniter
Requires-Dist: python-dateutil
Requires-Dist: Markdown
Requires-Dist: CairoSVG>=2.7.1
Requires-Dist: pdfkit>=1.0.0
